autovox/__init__.py
autovox/agents/__init__.py
autovox/agents/langgraph.py
autovox/core/__init__.py
autovox/core/protocol.py
autovox/engines/__init__.py
autovox/engines/gemini_realtime.py
autovox/engines/openai_realtime.py
autovox/engines/openai_webrtc.py
autovox-0.0.1.dist-info/METADATA
autovox-0.0.1.dist-info/WHEEL
autovox-0.0.1.dist-info/RECORD
