Metadata-Version: 2.4
Name: autovox
Version: 0.0.1
Summary: Voice Connector middleware for LangGraph agents
Project-URL: Homepage, https://github.com/mjunaidca/autovox
Project-URL: Issues, https://github.com/mjunaidca/autovox/issues
Project-URL: Documentation, https://github.com/mjunaidca/autovox#readme
Author-email: Muhammad Junaid <mr.junaidshaukat@gmail.com>
License: MIT
Classifier: Development Status :: 4 - Beta
Classifier: Intended Audience :: Developers
Classifier: License :: OSI Approved :: MIT License
Classifier: Programming Language :: Python :: 3
Classifier: Programming Language :: Python :: 3.11
Classifier: Topic :: Scientific/Engineering :: Artificial Intelligence
Classifier: Topic :: Software Development :: Libraries :: Python Modules
Requires-Python: >=3.11
Requires-Dist: elevenlabs>=1.0.0
Requires-Dist: google-genai>=1.3.0
Requires-Dist: google-generativeai>=0.8.0
Requires-Dist: langgraph>=0.3.2
Requires-Dist: numpy>=2.2.3
Requires-Dist: openai>=1.0.0
Requires-Dist: pyaudio>=0.2.14
Requires-Dist: pydantic>=2.0.0
Requires-Dist: python-dotenv>=1.0.0
Requires-Dist: typing-extensions>=4.0.0
Requires-Dist: websockets>=12.0
Provides-Extra: audio
Requires-Dist: numpy>=1.24.0; extra == 'audio'
Requires-Dist: pyaudio>=0.2.13; extra == 'audio'
Provides-Extra: dev
Requires-Dist: black>=23.0.0; extra == 'dev'
Requires-Dist: isort>=5.0.0; extra == 'dev'
Requires-Dist: pytest>=7.0.0; extra == 'dev'
Requires-Dist: ruff>=0.0.1; extra == 'dev'
